{
  "$schema": "https://developer.microsoft.com/json-schemas/fabric/item/report/definition/visualContainer/2.10.0/schema.json",
  "name": "2a4d06a2743108b32365",
  "position": {
    "x": 19.211042061006047,
    "y": 127.61620797668303,
    "z": 0,
    "height": 128.98842526675489,
    "width": 296.39893465552188,
    "tabOrder": 0
  },
  "visual": {
    "visualType": "slicer",
    "query": {
      "queryState": {
        "Values": {
          "projections": [
            {
              "field": {
                "Column": {
                  "Expression": {
                    "SourceRef": {
                      "Entity": "sample_sales_dataset"
                    }
                  },
                  "Property": "Date"
                }
              },
              "queryRef": "sample_sales_dataset.Date",
              "nativeQueryRef": "Date",
              "active": true
            }
          ]
        }
      },
      "sortDefinition": {
        "sort": [
          {
            "field": {
              "Column": {
                "Expression": {
                  "SourceRef": {
                    "Entity": "sample_sales_dataset"
                  }
                },
                "Property": "Date"
              }
            },
            "direction": "Ascending"
          }
        ],
        "isDefaultSort": true
      }
    },
    "objects": {
      "data": [
        {
          "properties": {
            "mode": {
              "expr": {
                "Literal": {
                  "Value": "'Between'"
                }
              }
            }
          }
        }
      ]
    },
    "drillFilterOtherVisuals": true
  },
  "filterConfig": {
    "filters": [
      {
        "name": "cb27a2489bd73777bb4a",
        "field": {
          "Column": {
            "Expression": {
              "SourceRef": {
                "Entity": "sample_sales_dataset"
              }
            },
            "Property": "Date"
          }
        },
        "type": "Categorical"
      }
    ]
  }
}